private_pypi_bundles/__init__.py
private_pypi-0.2.0.dist-info/entry_points.txt
private_pypi-0.2.0.dist-info/LICENSE
private_pypi-0.2.0.dist-info/WHEEL
private_pypi-0.2.0.dist-info/METADATA
private_pypi-0.2.0.dist-info/RECORD
